[{
  "_id": {
    "$oid": "653938571ebfe330733d7c90"
  },
  "name": "Ô Long Xoài Kem Cà Phê",
  "images": [
    {
      "url": "https://res.cloudinary.com/ddx8kaolc/image/upload/v1698248777/muic0u01iw2y3k80voss.jpg",
      "publicId": "muic0u01iw2y3k80voss",
      "filename": "O-Long-xoai-kem-coffee",
      "_id": {
        "$oid": "653938571ebfe330733d7c91"
      }
    }
  ],
  "description": "Chưa có thông tin.",
  "sale": 11323,
  "category": {
    "$oid": "6539376a1ebfe330733d7c69"
  },
  "sizes": [
    {
      "$oid": "653937941ebfe330733d7c7b"
    },
    {
      "$oid": "6539379f1ebfe330733d7c7f"
    },
    {
      "$oid": "653937a91ebfe330733d7c83"
    }
  ],
  "toppings": [
    {
      "$oid": "653936a21ebfe330733d7c49"
    },
    {
      "$oid": "653936b31ebfe330733d7c4c"
    },
    {
      "$oid": "653936c41ebfe330733d7c4f"
    },
    {
      "$oid": "653936d41ebfe330733d7c52"
    },
    {
      "$oid": "653936e21ebfe330733d7c55"
    },
    {
      "$oid": "653936f41ebfe330733d7c58"
    },
    {
      "$oid": "653937011ebfe330733d7c5b"
    },
    {
      "$oid": "653937181ebfe330733d7c5e"
    }
  ],
  "is_deleted": false,
  "is_active": true,
  "createdAt": {
    "$date": "2023-10-25T15:46:31.777Z"
  },
  "updatedAt": {
    "$date": "2023-12-16T08:31:01.394Z"
  }
},{
  "_id": {
    "$oid": "653938af1ebfe330733d7caa"
  },
  "name": "Trà Đào Bưởi Hồng Trân Châu Baby",
  "images": [
    {
      "url": "https://res.cloudinary.com/ddx8kaolc/image/upload/v1698248852/t6wknoge1swohk45mqb4.jpg",
      "publicId": "t6wknoge1swohk45mqb4",
      "filename": "Tra-dao-buoi-hong-tran-chau-baby (1)",
      "_id": {
        "$oid": "653938af1ebfe330733d7cab"
      }
    }
  ],
  "description": "Chưa có thông tin.",
  "sale": 3000,
  "category": {
    "$oid": "6539376a1ebfe330733d7c69"
  },
  "sizes": [
    {
      "$oid": "653937a91ebfe330733d7c83"
    },
    {
      "$oid": "6539379f1ebfe330733d7c7f"
    },
    {
      "$oid": "653937941ebfe330733d7c7b"
    }
  ],
  "toppings": [
    {
      "$oid": "653936a21ebfe330733d7c49"
    },
    {
      "$oid": "653936b31ebfe330733d7c4c"
    },
    {
      "$oid": "653936c41ebfe330733d7c4f"
    },
    {
      "$oid": "653936d41ebfe330733d7c52"
    },
    {
      "$oid": "653936e21ebfe330733d7c55"
    },
    {
      "$oid": "653936f41ebfe330733d7c58"
    },
    {
      "$oid": "653937011ebfe330733d7c5b"
    },
    {
      "$oid": "653937181ebfe330733d7c5e"
    }
  ],
  "is_deleted": false,
  "is_active": true,
  "createdAt": {
    "$date": "2023-10-25T15:47:59.162Z"
  },
  "updatedAt": {
    "$date": "2023-12-16T08:31:07.058Z"
  }
},{
  "_id": {
    "$oid": "653939511ebfe330733d7ccc"
  },
  "name": "Trà Xoài Bưởi Hồng",
  "images": [
    {
      "url": "https://res.cloudinary.com/ddx8kaolc/image/upload/v1698248976/wp5vgssf1vnzns5peh4j.png",
      "publicId": "wp5vgssf1vnzns5peh4j",
      "filename": "trà-xoài-bưởi-hồng",
      "_id": {
        "$oid": "653939511ebfe330733d7ccd"
      }
    }
  ],
  "description": "Chưa có thông tin.",
  "sale": 2000,
  "category": {
    "$oid": "6539376a1ebfe330733d7c69"
  },
  "sizes": [
    {
      "$oid": "653937941ebfe330733d7c7b"
    },
    {
      "$oid": "6539379f1ebfe330733d7c7f"
    },
    {
      "$oid": "653937a91ebfe330733d7c83"
    }
  ],
  "toppings": [
    {
      "$oid": "653936a21ebfe330733d7c49"
    },
    {
      "$oid": "653936b31ebfe330733d7c4c"
    },
    {
      "$oid": "653936c41ebfe330733d7c4f"
    },
    {
      "$oid": "653936d41ebfe330733d7c52"
    },
    {
      "$oid": "653936e21ebfe330733d7c55"
    },
    {
      "$oid": "653936f41ebfe330733d7c58"
    },
    {
      "$oid": "653937011ebfe330733d7c5b"
    },
    {
      "$oid": "653937181ebfe330733d7c5e"
    }
  ],
  "is_deleted": true,
  "is_active": true,
  "createdAt": {
    "$date": "2023-10-25T15:50:41.296Z"
  },
  "updatedAt": {
    "$date": "2023-12-11T19:04:26.775Z"
  }
},{
  "_id": {
    "$oid": "65393c58c9f403e70237c0ae"
  },
  "name": "Probi Bưởi Trân Châu Sương Mai",
  "images": [
    {
      "url": "https://res.cloudinary.com/ddx8kaolc/image/upload/v1698249809/zbuxcpf1avkdhdw9ardc.jpg",
      "publicId": "zbuxcpf1avkdhdw9ardc",
      "filename": "ezgif.com-gif-maker-2",
      "_id": {
        "$oid": "65393c58c9f403e70237c0af"
      }
    }
  ],
  "description": "chưa có thông tin",
  "sale": 1000,
  "category": {
    "$oid": "6539376a1ebfe330733d7c69"
  },
  "sizes": [
    {
      "$oid": "65393c58c9f403e70237c0ac"
    },
    {
      "$oid": "653937a91ebfe330733d7c83"
    },
    {
      "$oid": "6539379f1ebfe330733d7c7f"
    },
    {
      "$oid": "653937941ebfe330733d7c7b"
    }
  ],
  "toppings": [
    {
      "$oid": "653937181ebfe330733d7c5e"
    },
    {
      "$oid": "653937011ebfe330733d7c5b"
    },
    {
      "$oid": "653936f41ebfe330733d7c58"
    },
    {
      "$oid": "653936e21ebfe330733d7c55"
    },
    {
      "$oid": "653936d41ebfe330733d7c52"
    },
    {
      "$oid": "653936c41ebfe330733d7c4f"
    },
    {
      "$oid": "653936a21ebfe330733d7c49"
    },
    {
      "$oid": "653936b31ebfe330733d7c4c"
    }
  ],
  "is_deleted": true,
  "is_active": false,
  "createdAt": {
    "$date": "2023-10-25T16:03:36.692Z"
  },
  "updatedAt": {
    "$date": "2023-12-11T19:04:26.775Z"
  }
},{
  "_id": {
    "$oid": "65393e2ac9f403e70237c15a"
  },
  "name": "Trà Xoài Bưởi Hồng Kem Phô Mai",
  "images": [
    {
      "url": "https://res.cloudinary.com/ddx8kaolc/image/upload/v1698250274/aal0x3i0bzrixwavqr6u.png",
      "publicId": "aal0x3i0bzrixwavqr6u",
      "filename": "trà-xoài-bưởi-hồng-kem-phô-mai",
      "_id": {
        "$oid": "65393e2ac9f403e70237c15b"
      }
    }
  ],
  "description": "chưa có thông tin",
  "sale": 0,
  "category": {
    "$oid": "653937781ebfe330733d7c71"
  },
  "sizes": [
    {
      "$oid": "6539379f1ebfe330733d7c7f"
    },
    {
      "$oid": "653937941ebfe330733d7c7b"
    },
    {
      "$oid": "653937a91ebfe330733d7c83"
    }
  ],
  "toppings": [
    {
      "$oid": "653937181ebfe330733d7c5e"
    },
    {
      "$oid": "653937011ebfe330733d7c5b"
    },
    {
      "$oid": "653936f41ebfe330733d7c58"
    },
    {
      "$oid": "653936e21ebfe330733d7c55"
    },
    {
      "$oid": "653936d41ebfe330733d7c52"
    },
    {
      "$oid": "653936c41ebfe330733d7c4f"
    },
    {
      "$oid": "653936b31ebfe330733d7c4c"
    },
    {
      "$oid": "653936a21ebfe330733d7c49"
    }
  ],
  "is_deleted": true,
  "is_active": false,
  "createdAt": {
    "$date": "2023-10-25T16:11:22.841Z"
  },
  "updatedAt": {
    "$date": "2023-11-18T14:20:17.716Z"
  }
},{
  "_id": {
    "$oid": "65393e78c9f403e70237c187"
  },
  "name": "Choco Ngũ Cốc Kem Cafe",
  "images": [
    {
      "url": "https://res.cloudinary.com/ddx8kaolc/image/upload/v1698250355/lzlsczocjpgiivzjom3h.png",
      "publicId": "lzlsczocjpgiivzjom3h",
      "filename": "Hình-ảnh-sp-website_1000x1000_choco-ngũ-cốc-kem-cafe",
      "_id": {
        "$oid": "65393e78c9f403e70237c188"
      }
    }
  ],
  "description": "chưa có thông tin",
  "sale": 0,
  "category": {
    "$oid": "653937781ebfe330733d7c71"
  },
  "sizes": [
    {
      "$oid": "653937a91ebfe330733d7c83"
    },
    {
      "$oid": "6539379f1ebfe330733d7c7f"
    },
    {
      "$oid": "653937941ebfe330733d7c7b"
    }
  ],
  "toppings": [
    {
      "$oid": "653937181ebfe330733d7c5e"
    },
    {
      "$oid": "653937011ebfe330733d7c5b"
    },
    {
      "$oid": "653936f41ebfe330733d7c58"
    },
    {
      "$oid": "653936e21ebfe330733d7c55"
    },
    {
      "$oid": "653936d41ebfe330733d7c52"
    },
    {
      "$oid": "653936c41ebfe330733d7c4f"
    },
    {
      "$oid": "653936a21ebfe330733d7c49"
    },
    {
      "$oid": "653936b31ebfe330733d7c4c"
    }
  ],
  "is_deleted": true,
  "is_active": true,
  "createdAt": {
    "$date": "2023-10-25T16:12:40.629Z"
  },
  "updatedAt": {
    "$date": "2023-12-12T10:26:15.043Z"
  }
},{
  "_id": {
    "$oid": "65393eb0c9f403e70237c1b6"
  },
  "name": "Hồng Trà Ngũ Cốc Kem Cafe",
  "images": [
    {
      "url": "https://res.cloudinary.com/ddx8kaolc/image/upload/v1698250411/tb9mnsmgnyroptj1p7am.png",
      "publicId": "tb9mnsmgnyroptj1p7am",
      "filename": "Hình-ảnh-sp-website_1000x1000_hồng-trà-ngũ-cốc-kem-cafe",
      "_id": {
        "$oid": "65393eb0c9f403e70237c1b7"
      }
    }
  ],
  "description": "chưa có sản phẩm",
  "sale": 3322,
  "category": {
    "$oid": "653937781ebfe330733d7c71"
  },
  "sizes": [
    {
      "$oid": "653937a91ebfe330733d7c83"
    },
    {
      "$oid": "6539379f1ebfe330733d7c7f"
    },
    {
      "$oid": "653937941ebfe330733d7c7b"
    }
  ],
  "toppings": [
    {
      "$oid": "653937181ebfe330733d7c5e"
    },
    {
      "$oid": "653937011ebfe330733d7c5b"
    },
    {
      "$oid": "653936f41ebfe330733d7c58"
    },
    {
      "$oid": "653936e21ebfe330733d7c55"
    },
    {
      "$oid": "653936d41ebfe330733d7c52"
    },
    {
      "$oid": "653936c41ebfe330733d7c4f"
    },
    {
      "$oid": "653936b31ebfe330733d7c4c"
    },
    {
      "$oid": "653936a21ebfe330733d7c49"
    }
  ],
  "is_deleted": false,
  "is_active": true,
  "createdAt": {
    "$date": "2023-10-25T16:13:36.178Z"
  },
  "updatedAt": {
    "$date": "2023-12-06T11:21:41.413Z"
  }
},{
  "_id": {
    "$oid": "65393fb5c9f403e70237c2d4"
  },
  "name": "Dâu Tằm Kem Phô Mai",
  "images": [
    {
      "url": "https://res.cloudinary.com/ddx8kaolc/image/upload/v1698250533/k3403vu1t6fhdurbiavn.jpg",
      "publicId": "k3403vu1t6fhdurbiavn",
      "filename": "dau_tam_kem_pho_mai_09a4c4b857694d918a86542225fc2867_grande",
      "_id": {
        "$oid": "65393fb5c9f403e70237c2d5"
      }
    }
  ],
  "description": "Chưa có thông tin.",
  "sale": 0,
  "category": {
    "$oid": "653937781ebfe330733d7c71"
  },
  "sizes": [
    {
      "$oid": "65393fb5c9f403e70237c2d2"
    },
    {
      "$oid": "653937a91ebfe330733d7c83"
    },
    {
      "$oid": "6539379f1ebfe330733d7c7f"
    },
    {
      "$oid": "653937941ebfe330733d7c7b"
    }
  ],
  "toppings": [
    {
      "$oid": "653937011ebfe330733d7c5b"
    },
    {
      "$oid": "653937181ebfe330733d7c5e"
    },
    {
      "$oid": "653936f41ebfe330733d7c58"
    },
    {
      "$oid": "653936e21ebfe330733d7c55"
    },
    {
      "$oid": "653936d41ebfe330733d7c52"
    },
    {
      "$oid": "653936c41ebfe330733d7c4f"
    },
    {
      "$oid": "653936b31ebfe330733d7c4c"
    },
    {
      "$oid": "653936a21ebfe330733d7c49"
    }
  ],
  "is_deleted": false,
  "is_active": false,
  "createdAt": {
    "$date": "2023-10-25T16:17:57.461Z"
  },
  "updatedAt": {
    "$date": "2023-12-16T08:13:30.446Z"
  }
},{
  "_id": {
    "$oid": "6539402ac9f403e70237c32b"
  },
  "name": "Matcha Kem Phô Mai",
  "images": [
    {
      "url": "https://res.cloudinary.com/ddx8kaolc/image/upload/v1698250757/qbxi8ggus9nu07vjoq5d.png",
      "publicId": "qbxi8ggus9nu07vjoq5d",
      "filename": "matcha-kem-pho-mai_09b3b54997614aea86d2b61bcd7f548c_73a9e7cd539949718b13b06c5db9522f_grande",
      "_id": {
        "$oid": "6539402ac9f403e70237c32c"
      }
    }
  ],
  "description": "chưa có thông tin sản phẩm",
  "sale": 0,
  "category": {
    "$oid": "653937781ebfe330733d7c71"
  },
  "sizes": [
    {
      "$oid": "65394029c9f403e70237c329"
    },
    {
      "$oid": "6539379f1ebfe330733d7c7f"
    },
    {
      "$oid": "653937941ebfe330733d7c7b"
    }
  ],
  "toppings": [
    {
      "$oid": "653937181ebfe330733d7c5e"
    },
    {
      "$oid": "653937011ebfe330733d7c5b"
    },
    {
      "$oid": "653936f41ebfe330733d7c58"
    },
    {
      "$oid": "653936e21ebfe330733d7c55"
    },
    {
      "$oid": "653936d41ebfe330733d7c52"
    },
    {
      "$oid": "653936c41ebfe330733d7c4f"
    },
    {
      "$oid": "653936b31ebfe330733d7c4c"
    },
    {
      "$oid": "653936a21ebfe330733d7c49"
    }
  ],
  "is_deleted": false,
  "is_active": false,
  "createdAt": {
    "$date": "2023-10-25T16:19:54.091Z"
  },
  "updatedAt": {
    "$date": "2023-12-16T08:13:27.003Z"
  }
},{
  "_id": {
    "$oid": "653942f6c9f403e70237c45c"
  },
  "name": "Sữa Chua Dâu Tằm Hoàng Kim",
  "images": [
    {
      "url": "https://res.cloudinary.com/ddx8kaolc/image/upload/v1698251492/nsenkugtawjtuz3iqz1p.png",
      "publicId": "nsenkugtawjtuz3iqz1p",
      "filename": "sua-chua-dau-tam-hoang-kim",
      "_id": {
        "$oid": "653942f6c9f403e70237c45d"
      }
    }
  ],
  "description": "oke",
  "sale": 0,
  "category": {
    "$oid": "6539377f1ebfe330733d7c75"
  },
  "sizes": [
    {
      "$oid": "653942f6c9f403e70237c45a"
    },
    {
      "$oid": "653937a91ebfe330733d7c83"
    },
    {
      "$oid": "6539379f1ebfe330733d7c7f"
    },
    {
      "$oid": "653937941ebfe330733d7c7b"
    }
  ],
  "toppings": [
    {
      "$oid": "653937181ebfe330733d7c5e"
    },
    {
      "$oid": "653937011ebfe330733d7c5b"
    },
    {
      "$oid": "653936f41ebfe330733d7c58"
    },
    {
      "$oid": "653936e21ebfe330733d7c55"
    },
    {
      "$oid": "653936d41ebfe330733d7c52"
    },
    {
      "$oid": "653936c41ebfe330733d7c4f"
    },
    {
      "$oid": "653936b31ebfe330733d7c4c"
    },
    {
      "$oid": "653936a21ebfe330733d7c49"
    },
    {
      "$oid": "653937301ebfe330733d7c64"
    },
    {
      "$oid": "653937261ebfe330733d7c61"
    }
  ],
  "is_deleted": true,
  "is_active": true,
  "createdAt": {
    "$date": "2023-10-25T16:31:50.910Z"
  },
  "updatedAt": {
    "$date": "2023-12-14T07:06:20.952Z"
  }
},{
  "_id": {
    "$oid": "65394400eb12d80a743cd105"
  },
  "name": "Sữa Chua Dâu Tằm Hạt Dẻ",
  "images": [
    {
      "url": "https://res.cloudinary.com/ddx8kaolc/image/upload/v1698251769/kdchg3dmvskoayshfaqs.png",
      "publicId": "kdchg3dmvskoayshfaqs",
      "filename": "sua-chua-dau-tam-hat-de-",
      "_id": {
        "$oid": "65394400eb12d80a743cd106"
      }
    }
  ],
  "description": "oke",
  "sale": 0,
  "category": {
    "$oid": "6539377f1ebfe330733d7c75"
  },
  "sizes": [
    {
      "$oid": "653937a91ebfe330733d7c83"
    },
    {
      "$oid": "6539379f1ebfe330733d7c7f"
    },
    {
      "$oid": "653937941ebfe330733d7c7b"
    }
  ],
  "toppings": [
    {
      "$oid": "653937181ebfe330733d7c5e"
    },
    {
      "$oid": "653937011ebfe330733d7c5b"
    },
    {
      "$oid": "653936f41ebfe330733d7c58"
    },
    {
      "$oid": "653936d41ebfe330733d7c52"
    },
    {
      "$oid": "653936e21ebfe330733d7c55"
    },
    {
      "$oid": "653936c41ebfe330733d7c4f"
    },
    {
      "$oid": "653936b31ebfe330733d7c4c"
    },
    {
      "$oid": "653936a21ebfe330733d7c49"
    }
  ],
  "is_deleted": false,
  "is_active": true,
  "createdAt": {
    "$date": "2023-10-25T16:36:16.065Z"
  },
  "updatedAt": {
    "$date": "2023-12-16T08:21:43.469Z"
  }
},{
  "_id": {
    "$oid": "653944b5eb12d80a743cd126"
  },
  "name": "Sữa Chua Trắng",
  "images": [
    {
      "url": "https://res.cloudinary.com/ddx8kaolc/image/upload/v1698251952/inlxz9qj92k1rbpzyyhx.png",
      "publicId": "inlxz9qj92k1rbpzyyhx",
      "filename": "sua-chua-trang-",
      "_id": {
        "$oid": "653944b5eb12d80a743cd127"
      }
    }
  ],
  "description": "oke",
  "sale": 5000,
  "category": {
    "$oid": "6539377f1ebfe330733d7c75"
  },
  "sizes": [
    {
      "$oid": "653937a91ebfe330733d7c83"
    },
    {
      "$oid": "6539379f1ebfe330733d7c7f"
    },
    {
      "$oid": "653937941ebfe330733d7c7b"
    }
  ],
  "toppings": [
    {
      "$oid": "653937181ebfe330733d7c5e"
    },
    {
      "$oid": "653937011ebfe330733d7c5b"
    },
    {
      "$oid": "653936f41ebfe330733d7c58"
    },
    {
      "$oid": "653936e21ebfe330733d7c55"
    },
    {
      "$oid": "653936d41ebfe330733d7c52"
    },
    {
      "$oid": "653936c41ebfe330733d7c4f"
    },
    {
      "$oid": "653936a21ebfe330733d7c49"
    },
    {
      "$oid": "653936b31ebfe330733d7c4c"
    }
  ],
  "is_deleted": false,
  "is_active": true,
  "createdAt": {
    "$date": "2023-10-25T16:39:17.130Z"
  },
  "updatedAt": {
    "$date": "2023-12-16T08:21:39.326Z"
  }
},{
  "_id": {
    "$oid": "6539453beb12d80a743cd162"
  },
  "name": "Trà dâu tằm pha lê tuyết",
  "images": [
    {
      "url": "https://res.cloudinary.com/ddx8kaolc/image/upload/v1698252050/tjqgzsyionkj4rnj4lqu.jpg",
      "publicId": "tjqgzsyionkj4rnj4lqu",
      "filename": "dâu-tằm-pha-lê-tuyết",
      "_id": {
        "$oid": "6539453beb12d80a743cd163"
      }
    }
  ],
  "description": "oke",
  "sale": 1000,
  "category": {
    "$oid": "653937711ebfe330733d7c6d"
  },
  "sizes": [
    {
      "$oid": "6539453beb12d80a743cd15e"
    },
    {
      "$oid": "6539453beb12d80a743cd160"
    },
    {
      "$oid": "6539379f1ebfe330733d7c7f"
    },
    {
      "$oid": "653937941ebfe330733d7c7b"
    }
  ],
  "toppings": [
    {
      "$oid": "653937181ebfe330733d7c5e"
    },
    {
      "$oid": "653937011ebfe330733d7c5b"
    },
    {
      "$oid": "653936f41ebfe330733d7c58"
    },
    {
      "$oid": "653936e21ebfe330733d7c55"
    },
    {
      "$oid": "653936d41ebfe330733d7c52"
    },
    {
      "$oid": "653936c41ebfe330733d7c4f"
    },
    {
      "$oid": "653936a21ebfe330733d7c49"
    },
    {
      "$oid": "653936b31ebfe330733d7c4c"
    }
  ],
  "is_deleted": false,
  "is_active": true,
  "createdAt": {
    "$date": "2023-10-25T16:41:31.380Z"
  },
  "updatedAt": {
    "$date": "2023-12-16T08:29:29.000Z"
  }
},{
  "_id": {
    "$oid": "653e8a7b5288babc1caed3cb"
  },
  "name": "Trà Dâu Tằm",
  "images": [
    {
      "url": "https://res.cloudinary.com/ddx8kaolc/image/upload/v1698597494/ikka353oxd4ednwkvqdr.jpg",
      "publicId": "ikka353oxd4ednwkvqdr",
      "filename": "tjqgzsyionkj4rnj4lqu",
      "_id": {
        "$oid": "653e8a7b5288babc1caed3cc"
      }
    }
  ],
  "description": "azzz",
  "sale": 2000,
  "category": {
    "$oid": "6539377f1ebfe330733d7c75"
  },
  "sizes": [
    {
      "$oid": "653937a91ebfe330733d7c83"
    }
  ],
  "toppings": [
    {
      "$oid": "653936a21ebfe330733d7c49"
    }
  ],
  "is_deleted": false,
  "is_active": true,
  "createdAt": {
    "$date": "2023-10-29T16:38:19.060Z"
  },
  "updatedAt": {
    "$date": "2023-12-16T08:21:34.379Z"
  }
},{
  "_id": {
    "$oid": "653fcab9752c6ea08ea07dbd"
  },
  "name": "Hồng Trà",
  "images": [
    {
      "url": "https://res.cloudinary.com/ddx8kaolc/image/upload/v1701854630/ug7zvvcg8tlpvliubflu.jpg",
      "publicId": "ug7zvvcg8tlpvliubflu",
      "filename": "1578304012347_hong_tra_f8b228ea2b0147a5b05c9292569deea7_grande",
      "_id": {
        "$oid": "65703dc25f65584abe3425d8"
      }
    }
  ],
  "description": "Ngon",
  "sale": 10000,
  "category": {
    "$oid": "6539376a1ebfe330733d7c69"
  },
  "sizes": [
    {
      "$oid": "653fcab9752c6ea08ea07db7"
    },
    {
      "$oid": "653fcab9752c6ea08ea07db9"
    },
    {
      "$oid": "653fcab9752c6ea08ea07dbb"
    },
    {
      "$oid": "653937a91ebfe330733d7c83"
    }
  ],
  "toppings": [
    {
      "$oid": "653936f41ebfe330733d7c58"
    },
    {
      "$oid": "653937181ebfe330733d7c5e"
    },
    {
      "$oid": "653936a21ebfe330733d7c49"
    }
  ],
  "is_deleted": false,
  "is_active": true,
  "createdAt": {
    "$date": "2023-10-30T15:24:41.945Z"
  },
  "updatedAt": {
    "$date": "2023-12-16T08:21:32.088Z"
  }
},{
  "_id": {
    "$oid": "6571dd258f07589ca8768287"
  },
  "name": "Sữa kem lắc đào",
  "images": [
    {
      "url": "https://res.cloudinary.com/ddx8kaolc/image/upload/v1701960985/mc8o9psrzqik1zcnygat.jpg",
      "publicId": "mc8o9psrzqik1zcnygat",
      "filename": "dâu-tằm-pha-lê-tuyết",
      "_id": {
        "$oid": "6571dd258f07589ca8768288"
      }
    }
  ],
  "description": "mô tả sản phẩm",
  "sale": 10000,
  "category": {
    "$oid": "653937781ebfe330733d7c71"
  },
  "sizes": [
    {
      "$oid": "6571dd248f07589ca8768285"
    },
    {
      "$oid": "653937941ebfe330733d7c7b"
    }
  ],
  "toppings": [
    {
      "$oid": "656ef1d3dc642a3ebeee10e0"
    },
    {
      "$oid": "653936f41ebfe330733d7c58"
    },
    {
      "$oid": "653937301ebfe330733d7c64"
    },
    {
      "$oid": "656ef2b1dc642a3ebeee10ef"
    },
    {
      "$oid": "653937011ebfe330733d7c5b"
    },
    {
      "$oid": "653937181ebfe330733d7c5e"
    },
    {
      "$oid": "653937261ebfe330733d7c61"
    }
  ],
  "is_deleted": false,
  "is_active": true,
  "createdAt": {
    "$date": "2023-12-07T14:56:37.213Z"
  },
  "updatedAt": {
    "$date": "2023-12-16T08:21:16.126Z"
  }
},{
  "_id": {
    "$oid": "657d528ffde7defde3122328"
  },
  "name": "Trà Chanh Mật Ong Giã Tay",
  "images": [
    {
      "url": "https://res.cloudinary.com/ddx8kaolc/image/upload/v1702711944/uw92qr73jtz6jrkbjkeu.jpg",
      "publicId": "uw92qr73jtz6jrkbjkeu",
      "filename": "z4925614520640_1babe5daea83472f4784ceb3cd206979",
      "_id": {
        "$oid": "657d528ffde7defde3122329"
      }
    }
  ],
  "description": "Quá ngon luôn",
  "sale": 5000,
  "category": {
    "$oid": "653937711ebfe330733d7c6d"
  },
  "sizes": [
    {
      "$oid": "653937a91ebfe330733d7c83"
    }
  ],
  "toppings": [
    {
      "$oid": "653936d41ebfe330733d7c52"
    },
    {
      "$oid": "653936c41ebfe330733d7c4f"
    },
    {
      "$oid": "653936b31ebfe330733d7c4c"
    },
    {
      "$oid": "653936a21ebfe330733d7c49"
    }
  ],
  "is_deleted": false,
  "is_active": true,
  "createdAt": {
    "$date": "2023-12-16T07:32:31.216Z"
  },
  "updatedAt": {
    "$date": "2023-12-16T08:37:50.567Z"
  }
},{
  "_id": {
    "$oid": "657d5307fde7defde3122379"
  },
  "name": "Trà Chanh Mật Ong Giã Tay Khổng Lồ",
  "images": [
    {
      "url": "https://res.cloudinary.com/ddx8kaolc/image/upload/v1702712047/rpi06sjpxnpxd3trqmwt.jpg",
      "publicId": "rpi06sjpxnpxd3trqmwt",
      "filename": "z4967287161207_d582f10a876bcc7359666df4f2ec76c5",
      "_id": {
        "$oid": "657d5307fde7defde312237a"
      }
    }
  ],
  "description": "Ngon hơn khi uống lạnh!",
  "sale": 5000,
  "category": {
    "$oid": "653937711ebfe330733d7c6d"
  },
  "sizes": [
    {
      "$oid": "657d5307fde7defde3122377"
    },
    {
      "$oid": "6539379f1ebfe330733d7c7f"
    }
  ],
  "toppings": [
    {
      "$oid": "653937011ebfe330733d7c5b"
    },
    {
      "$oid": "653936f41ebfe330733d7c58"
    },
    {
      "$oid": "653936a21ebfe330733d7c49"
    },
    {
      "$oid": "653936b31ebfe330733d7c4c"
    }
  ],
  "is_deleted": false,
  "is_active": true,
  "createdAt": {
    "$date": "2023-12-16T07:34:31.345Z"
  },
  "updatedAt": {
    "$date": "2023-12-16T08:21:08.525Z"
  }
},{
  "_id": {
    "$oid": "657d5397fde7defde31223cf"
  },
  "name": "Ô Long Sữa Trân Châu Ngũ Cốc",
  "images": [
    {
      "url": "https://res.cloudinary.com/ddx8kaolc/image/upload/v1702712200/jjusvp0whqvvwysdvezz.jpg",
      "publicId": "jjusvp0whqvvwysdvezz",
      "filename": "z4925614515113_5bdf67d7e4b3ee98215ea11da9b303e9",
      "_id": {
        "$oid": "657d5397fde7defde31223d0"
      }
    }
  ],
  "description": "không có",
  "sale": 5000,
  "category": {
    "$oid": "653937711ebfe330733d7c6d"
  },
  "sizes": [
    {
      "$oid": "657d5397fde7defde31223cb"
    },
    {
      "$oid": "657d5397fde7defde31223cd"
    }
  ],
  "toppings": [
    {
      "$oid": "656ef1d3dc642a3ebeee10e0"
    },
    {
      "$oid": "653937301ebfe330733d7c64"
    },
    {
      "$oid": "653937261ebfe330733d7c61"
    },
    {
      "$oid": "653937181ebfe330733d7c5e"
    },
    {
      "$oid": "653937011ebfe330733d7c5b"
    },
    {
      "$oid": "653936f41ebfe330733d7c58"
    },
    {
      "$oid": "653936e21ebfe330733d7c55"
    },
    {
      "$oid": "653936d41ebfe330733d7c52"
    },
    {
      "$oid": "653936c41ebfe330733d7c4f"
    },
    {
      "$oid": "653936b31ebfe330733d7c4c"
    },
    {
      "$oid": "653936a21ebfe330733d7c49"
    },
    {
      "$oid": "656ef2b1dc642a3ebeee10ef"
    }
  ],
  "is_deleted": false,
  "is_active": false,
  "createdAt": {
    "$date": "2023-12-16T07:36:55.946Z"
  },
  "updatedAt": {
    "$date": "2023-12-19T15:15:17.331Z"
  }
},{
  "_id": {
    "$oid": "657d5efbd439172d525a545b"
  },
  "name": "Grass Jelly Milk Coffee",
  "images": [
    {
      "url": "https://res.cloudinary.com/ddx8kaolc/image/upload/v1702715125/q4livdzmtokd6jvq25gn.png",
      "publicId": "q4livdzmtokd6jvq25gn",
      "filename": "Grass-Jelly-Milk-Coffee",
      "_id": {
        "$oid": "657d5efbd439172d525a545c"
      }
    }
  ],
  "description": "Ngon",
  "sale": 2000,
  "category": {
    "$oid": "653937781ebfe330733d7c71"
  },
  "sizes": [
    {
      "$oid": "657d5efbd439172d525a5459"
    },
    {
      "$oid": "653937a91ebfe330733d7c83"
    }
  ],
  "toppings": [
    {
      "$oid": "656ef1d3dc642a3ebeee10e0"
    },
    {
      "$oid": "653937301ebfe330733d7c64"
    },
    {
      "$oid": "653937261ebfe330733d7c61"
    }
  ],
  "is_deleted": false,
  "is_active": true,
  "createdAt": {
    "$date": "2023-12-16T08:25:31.464Z"
  },
  "updatedAt": {
    "$date": "2023-12-19T02:38:54.765Z"
  }
},{
  "_id": {
    "$oid": "657d5fd2d439172d525a562b"
  },
  "name": "Trà sữa dâu tây ",
  "images": [
    {
      "url": "https://res.cloudinary.com/ddx8kaolc/image/upload/v1702715344/laj5hptt20urlbh6wz9o.jpg",
      "publicId": "laj5hptt20urlbh6wz9o",
      "filename": "Tra-Sua-Dau-Tay-2-copy",
      "_id": {
        "$oid": "657d5fd2d439172d525a562c"
      }
    }
  ],
  "description": "Ngonx2",
  "sale": 4000,
  "category": {
    "$oid": "653937711ebfe330733d7c6d"
  },
  "sizes": [
    {
      "$oid": "657d5fd2d439172d525a5629"
    },
    {
      "$oid": "653937a91ebfe330733d7c83"
    }
  ],
  "toppings": [
    {
      "$oid": "656ef2b1dc642a3ebeee10ef"
    },
    {
      "$oid": "656ef1d3dc642a3ebeee10e0"
    },
    {
      "$oid": "653937261ebfe330733d7c61"
    },
    {
      "$oid": "653937301ebfe330733d7c64"
    },
    {
      "$oid": "653937181ebfe330733d7c5e"
    },
    {
      "$oid": "653937011ebfe330733d7c5b"
    },
    {
      "$oid": "653936f41ebfe330733d7c58"
    },
    {
      "$oid": "653936e21ebfe330733d7c55"
    },
    {
      "$oid": "653936d41ebfe330733d7c52"
    },
    {
      "$oid": "653936c41ebfe330733d7c4f"
    },
    {
      "$oid": "653936b31ebfe330733d7c4c"
    },
    {
      "$oid": "653936a21ebfe330733d7c49"
    }
  ],
  "is_deleted": false,
  "is_active": true,
  "createdAt": {
    "$date": "2023-12-16T08:29:06.485Z"
  },
  "updatedAt": {
    "$date": "2023-12-18T17:10:55.995Z"
  }
},{
  "_id": {
    "$oid": "657f324897befed43e5dbea5"
  },
  "name": "Trà Đào Bốn Mùa",
  "images": [
    {
      "url": "https://res.cloudinary.com/ddx8kaolc/image/upload/v1702834753/ihxilyelx3armuqxiryz.jpg",
      "publicId": "ihxilyelx3armuqxiryz",
      "filename": "dâu-tằm-pha-lê-tuyết",
      "_id": {
        "$oid": "657f324897befed43e5dbea6"
      }
    }
  ],
  "description": "tesst",
  "sale": 3000,
  "category": {
    "$oid": "6539377f1ebfe330733d7c75"
  },
  "sizes": [
    {
      "$oid": "657f461fe8ca23703acf05e1"
    },
    {
      "$oid": "657f460ce8ca23703acf0595"
    },
    {
      "$oid": "6571e4048f07589ca8768a58"
    }
  ],
  "toppings": [
    {
      "$oid": "656ef1d3dc642a3ebeee10e0"
    },
    {
      "$oid": "653937011ebfe330733d7c5b"
    },
    {
      "$oid": "653937261ebfe330733d7c61"
    }
  ],
  "is_deleted": false,
  "is_active": true,
  "createdAt": {
    "$date": "2023-12-17T17:39:20.216Z"
  },
  "updatedAt": {
    "$date": "2023-12-19T02:45:55.723Z"
  }
},{
  "_id": {
    "$oid": "657f3f045ac45ac358c4e8c4"
  },
  "name": "Super Sundae Socola",
  "images": [
    {
      "url": "https://res.cloudinary.com/ddx8kaolc/image/upload/v1702838018/f61xytwwipo7dezj0uam.png",
      "publicId": "f61xytwwipo7dezj0uam",
      "filename": "sua-chua-trang-",
      "_id": {
        "$oid": "657f3f045ac45ac358c4e8c5"
      }
    }
  ],
  "description": "oke alo",
  "sale": 1000,
  "category": {
    "$oid": "653937781ebfe330733d7c71"
  },
  "sizes": [
    {
      "$oid": "657f461fe8ca23703acf05e1"
    },
    {
      "$oid": "657f3f045ac45ac358c4e8c2"
    },
    {
      "$oid": "6571e4048f07589ca8768a58"
    },
    {
      "$oid": "65749396fbe39e52f446254b"
    },
    {
      "$oid": "653937a91ebfe330733d7c83"
    },
    {
      "$oid": "657f3dba5ac45ac358c4e866"
    }
  ],
  "toppings": [
    {
      "$oid": "653937301ebfe330733d7c64"
    }
  ],
  "is_deleted": false,
  "is_active": false,
  "createdAt": {
    "$date": "2023-12-17T18:33:40.587Z"
  },
  "updatedAt": {
    "$date": "2023-12-18T17:11:28.595Z"
  }
},{
  "_id": {
    "$oid": "65807f0444176eadbe1086be"
  },
  "name": "Super Sundae Mâm Xôi",
  "images": [
    {
      "url": "https://res.cloudinary.com/ddx8kaolc/image/upload/v1702919934/a7kzufuiy7st4qqqj5s8.jpg",
      "publicId": "a7kzufuiy7st4qqqj5s8",
      "filename": "dau_tam_kem_pho_mai_09a4c4b857694d918a86542225fc2867_grande",
      "_id": {
        "$oid": "65807f0444176eadbe1086bf"
      }
    }
  ],
  "description": "Super Sundae Mâm Xôi",
  "sale": 0,
  "category": {
    "$oid": "653937711ebfe330733d7c6d"
  },
  "sizes": [
    {
      "$oid": "65807f0444176eadbe1086bc"
    },
    {
      "$oid": "6571e4048f07589ca8768a58"
    }
  ],
  "toppings": [
    {
      "$oid": "656ef2b1dc642a3ebeee10ef"
    },
    {
      "$oid": "656ef1d3dc642a3ebeee10e0"
    },
    {
      "$oid": "653937301ebfe330733d7c64"
    },
    {
      "$oid": "653937261ebfe330733d7c61"
    },
    {
      "$oid": "653937181ebfe330733d7c5e"
    }
  ],
  "is_deleted": false,
  "is_active": true,
  "createdAt": {
    "$date": "2023-12-18T17:19:00.293Z"
  },
  "updatedAt": {
    "$date": "2023-12-19T02:45:59.885Z"
  }
}]